codatsynccommerce/__init__.py
codatsynccommerce/accounting_accounts.py
codatsynccommerce/accounting_bank_accounts.py
codatsynccommerce/accounting_company_info.py
codatsynccommerce/accounting_credit_notes.py
codatsynccommerce/accounting_customers.py
codatsynccommerce/accounting_direct_incomes.py
codatsynccommerce/accounting_invoices.py
codatsynccommerce/accounting_journal_entries.py
codatsynccommerce/accounting_payments.py
codatsynccommerce/commerce_company_info.py
codatsynccommerce/commerce_customers.py
codatsynccommerce/commerce_locations.py
codatsynccommerce/commerce_orders.py
codatsynccommerce/commerce_payments.py
codatsynccommerce/commerce_products.py
codatsynccommerce/commerce_transactions.py
codatsynccommerce/companies.py
codatsynccommerce/company_management.py
codatsynccommerce/configuration.py
codatsynccommerce/connections.py
codatsynccommerce/integrations.py
codatsynccommerce/push_data.py
codatsynccommerce/refresh_data.py
codatsynccommerce/sdk.py
codatsynccommerce/sdkconfiguration.py
codatsynccommerce/sync.py
codatsynccommerce/sync_flow_preferences.py
codatsynccommerce/models/__init__.py
codatsynccommerce/models/errors/__init__.py
codatsynccommerce/models/errors/errormessage.py
codatsynccommerce/models/errors/sdkerror.py
codatsynccommerce/models/operations/__init__.py
codatsynccommerce/models/operations/create_accounting_account.py
codatsynccommerce/models/operations/create_accounting_credit_note.py
codatsynccommerce/models/operations/create_accounting_customer.py
codatsynccommerce/models/operations/create_accounting_direct_income.py
codatsynccommerce/models/operations/create_accounting_invoice.py
codatsynccommerce/models/operations/create_accounting_journal_entry.py
codatsynccommerce/models/operations/create_accounting_payment.py
codatsynccommerce/models/operations/create_company.py
codatsynccommerce/models/operations/create_connection.py
codatsynccommerce/models/operations/delete_company.py
codatsynccommerce/models/operations/delete_connection.py
codat_sync_for_commerce_version_1-0.3.0.dist-info/METADATA
codat_sync_for_commerce_version_1-0.3.0.dist-info/WHEEL
codat_sync_for_commerce_version_1-0.3.0.dist-info/top_level.txt
codat_sync_for_commerce_version_1-0.3.0.dist-info/RECORD
